{
    "world_size": 30720,
    "map_marker": [
        {
            "name": "outpost",
            "x": 23044.2,
            "y": 7272.19
        },
        {
            "name": "outpost_1",
            "x": 14832.2,
            "y": 11130.6
        },
        {
            "name": "outpost_2",
            "x": 19352.6,
            "y": 9680.44
        },
        {
            "name": "outpost_3",
            "x": 16839.3,
            "y": 12054.6
        },
        {
            "name": "outpost_4",
            "x": 21929.7,
            "y": 20978.2
        },
        {
            "name": "outpost_5",
            "x": 28324,
            "y": 25754.4
        },
        {
            "name": "outpost_6",
            "x": 25265.4,
            "y": 21799.9
        },
        {
            "name": "outpost_7",
            "x": 4842.51,
            "y": 21950.4
        },
        {
            "name": "outpost_8",
            "x": 20600.1,
            "y": 18815
        },
        {
            "name": "outpost_9",
            "x": 20627.3,
            "y": 20103.9
        },
        {
            "name": "outpost_10",
            "x": 16083.2,
            "y": 17002.7
        },
        {
            "name": "outpost_11",
            "x": 12479.8,
            "y": 15197.5
        },
        {
            "name": "outpost_12",
            "x": 9210.23,
            "y": 19280.6
        },
        {
            "name": "outpost_13",
            "x": 16583.9,
            "y": 19013.3
        },
        {
            "name": "outpost_14",
            "x": 3910.73,
            "y": 12293.9
        },
        {
            "name": "outpost_15",
            "x": 8915,
            "y": 7477
        },
        {
            "name": "outpost_16",
            "x": 13788.2,
            "y": 6374.5
        },
        {
            "name": "outpost_17",
            "x": 14275.2,
            "y": 16275.2
        },
        {
            "name": "outpost_18",
            "x": 18089.9,
            "y": 19181.3
        },
        {
            "name": "outpost_19",
            "x": 9707.48,
            "y": 22307.1
        },
        {
            "name": "outpost_20",
            "x": 18726.8,
            "y": 10212.5
        },
        {
            "name": "outpost_21",
            "x": 17869.2,
            "y": 11748.6
        },
        {
            "name": "outpost_22",
            "x": 6841.71,
            "y": 16108
        },
        {
            "name": "outpost_23",
            "x": 15176.1,
            "y": 17362.1
        },
        {
            "name": "outpost_24",
            "x": 26473.2,
            "y": 22189.6
        },
        {
            "name": "outpost_25",
            "x": 10013.5,
            "y": 11240.6
        },
        {
            "name": "outpost_26",
            "x": 4553.24,
            "y": 15432.4
        },
        {
            "name": "outpost_27",
            "x": 8393.26,
            "y": 18246.2
        },
        {
            "name": "outpost_28",
            "x": 9930.51,
            "y": 19386.3
        },
        {
            "name": "outpost_29",
            "x": 3097,
            "y": 13198.1
        },
        {
            "name": "outpost_30",
            "x": 6565.83,
            "y": 22679.8
        },
        {
            "name": "outpost_31",
            "x": 12850.1,
            "y": 16721.3
        },
        {
            "name": "outpost_32",
            "x": 8850.56,
            "y": 23451.6
        },
        {
            "name": "outpost_33",
            "x": 5473.03,
            "y": 15003.4
        },
        {
            "name": "outpost_34",
            "x": 14216,
            "y": 21225.7
        },
        {
            "name": "outpost_35",
            "x": 4276.18,
            "y": 20684.6
        },
        {
            "name": "outpost_36",
            "x": 23594.5,
            "y": 21100.3
        },
        {
            "name": "outpost_37",
            "x": 20940.7,
            "y": 19235.6
        },
        {
            "name": "outpost_38",
            "x": 20082.9,
            "y": 6728.34
        },
        {
            "name": "outpost_39",
            "x": 17436.4,
            "y": 13169.2
        },
        {
            "name": "outpost_40",
            "x": 12287.4,
            "y": 8888.12
        },
        {
            "name": "outpost_41",
            "x": 8291.45,
            "y": 10065.4
        },
        {
            "name": "outpost_42",
            "x": 5372.27,
            "y": 14237.1
        },
        {
            "name": "outpost_43",
            "x": 14065.5,
            "y": 22962
        },
        {
            "name": "resource",
            "x": 19616.7,
            "y": 15635.5
        },
        {
            "name": "resource_1",
            "x": 18466.5,
            "y": 14273.4
        },
        {
            "name": "resource_2",
            "x": 17098.7,
            "y": 11295.6
        },
        {
            "name": "resource_3",
            "x": 18292.9,
            "y": 15534.2
        },
        {
            "name": "resource_4",
            "x": 4432.55,
            "y": 12589.1
        },
        {
            "name": "resource_5",
            "x": 5890.09,
            "y": 20206.7
        },
        {
            "name": "resource_6",
            "x": 5955.31,
            "y": 12531.1
        },
        {
            "name": "resource_7",
            "x": 7550.84,
            "y": 12182.7
        },
        {
            "name": "factory",
            "x": 12628.2,
            "y": 16374.5
        },
        {
            "name": "factory_1",
            "x": 14340.1,
            "y": 18940.5
        },
        {
            "name": "factory_2",
            "x": 6339.82,
            "y": 14889.7
        },
        {
            "name": "factory_3",
            "x": 6191,
            "y": 16249
        },
        {
            "name": "factory_4",
            "x": 3269.96,
            "y": 12458.8
        },
        {
            "name": "factory_5",
            "x": 25413.3,
            "y": 20337.4
        },
        {
            "name": "factory_6",
            "x": 20671.3,
            "y": 15727
        },
        {
            "name": "factory_7",
            "x": 27005.3,
            "y": 21521.7
        },
        {
            "name": "factory_8",
            "x": 15324.9,
            "y": 16240.8
        },
        {
            "name": "factory_9",
            "x": 11013,
            "y": 12655
        },
        {
            "name": "factory_10",
            "x": 8226.34,
            "y": 10939.7
        },
        {
            "name": "factory_11",
            "x": 4214.49,
            "y": 15044.1
        },
        {
            "name": "airport",
            "x": 21017.9,
            "y": 7303.11
        },
        {
            "name": "airport_1",
            "x": 23074.8,
            "y": 18782.7
        },
        {
            "name": "airport_2",
            "x": 26955,
            "y": 24778.5
        },
        {
            "name": "airport_4",
            "x": 11503.5,
            "y": 11701.2
        },
        {
            "name": "airport_3",
            "x": 14778.7,
            "y": 16401.3
        },
        {
            "name": "airport_5",
            "x": 9087.75,
            "y": 21520.5
        },
        {
            "name": "seaport",
            "x": 16660.6,
            "y": 12307.6
        },
        {
            "name": "seaport_1",
            "x": 15391.1,
            "y": 15859.4
        },
        {
            "name": "seaport_3",
            "x": 20690.8,
            "y": 19468.6
        },
        {
            "name": "seaport_4",
            "x": 27607,
            "y": 24585.3
        },
        {
            "name": "seaport_2",
            "x": 3201.4,
            "y": 12895.5
        },
        {
            "name": "Aggelochori",
            "x": 3622.83,
            "y": 13779.5
        },
        {
            "name": "Neri",
            "x": 4114.33,
            "y": 11739.6
        },
        {
            "name": "Panochori",
            "x": 5008.85,
            "y": 11253.1
        },
        {
            "name": "Zaros",
            "x": 9086.33,
            "y": 11951.8
        },
        {
            "name": "Therisa",
            "x": 10638.6,
            "y": 12227.1
        },
        {
            "name": "Katalaki",
            "x": 11704.2,
            "y": 13675.1
        },
        {
            "name": "Neochori",
            "x": 12499.9,
            "y": 14325.4
        },
        {
            "name": "Stavros",
            "x": 12948.3,
            "y": 15048.8
        },
        {
            "name": "Lakka",
            "x": 12243.6,
            "y": 15744.3
        },
        {
            "name": "Alikampos",
            "x": 11111.5,
            "y": 14563.2
        },
        {
            "name": "Agios Dionysios",
            "x": 9178.99,
            "y": 15953.6
        },
        {
            "name": "Kore",
            "x": 7107.04,
            "y": 16435.3
        },
        {
            "name": "Negades",
            "x": 4874.81,
            "y": 16146
        },
        {
            "name": "Agios Konstantinos",
            "x": 3926.2,
            "y": 17276.2
        },
        {
            "name": "Topolia",
            "x": 7377.54,
            "y": 15434.7
        },
        {
            "name": "Gravia",
            "x": 14454.1,
            "y": 17627.9
        },
        {
            "name": "Athira",
            "x": 13997.3,
            "y": 18724.2
        },
        {
            "name": "Frini",
            "x": 14636.6,
            "y": 20796.3
        },
        {
            "name": "Ifestiona",
            "x": 12763.9,
            "y": 19666.1
        },
        {
            "name": "Syrta",
            "x": 8622.91,
            "y": 18294.5
        },
        {
            "name": "Galati",
            "x": 10248.5,
            "y": 19022.3
        },
        {
            "name": "Koroni",
            "x": 11786,
            "y": 18360.9
        },
        {
            "name": "Abdera",
            "x": 9410.17,
            "y": 20282.4
        },
        {
            "name": "Telos",
            "x": 16214.6,
            "y": 17299.8
        },
        {
            "name": "Anthrakia",
            "x": 16580.7,
            "y": 16112.8
        },
        {
            "name": "Kalithea",
            "x": 17826.6,
            "y": 18133.5
        },
        {
            "name": "Agios Petros",
            "x": 19336.9,
            "y": 17641
        },
        {
            "name": "Paros",
            "x": 20891,
            "y": 16982
        },
        {
            "name": "Kalochori",
            "x": 21342,
            "y": 16363.4
        },
        {
            "name": "Sofia",
            "x": 25679.6,
            "y": 21367.4
        },
        {
            "name": "Molos",
            "x": 26983.3,
            "y": 23211.1
        },
        {
            "name": "Ioannina",
            "x": 23186.5,
            "y": 19966.9
        },
        {
            "name": "Delfinaki",
            "x": 23924.4,
            "y": 20151.3
        },
        {
            "name": "Nifi",
            "x": 19497.2,
            "y": 15413.7
        },
        {
            "name": "Charkia",
            "x": 18042.1,
            "y": 15267.8
        },
        {
            "name": "Dorida",
            "x": 19343.3,
            "y": 13259
        },
        {
            "name": "Chalkeia",
            "x": 20173,
            "y": 11665.8
        },
        {
            "name": "Panagia",
            "x": 20465.4,
            "y": 8892.76
        },
        {
            "name": "Feres",
            "x": 21624.3,
            "y": 7546.59
        },
        {
            "name": "Selakano",
            "x": 20788.1,
            "y": 6729.06
        },
        {
            "name": "Pyrgos",
            "x": 16784.3,
            "y": 12603.8
        },
        {
            "name": "Kavala",
            "x": 3448.96,
            "y": 12989.4
        },
        {
            "name": "Poliakko",
            "x": 10962.5,
            "y": 13439
        },
        {
            "name": "Oreokastro",
            "x": 4566.51,
            "y": 21462.3
        },
        {
            "name": "Agia Triada",
            "x": 16688.7,
            "y": 20479.6
        },
        {
            "name": "Orino",
            "x": 10430.2,
            "y": 17227.8
        },
        {
            "name": "Ekali",
            "x": 17014,
            "y": 10051.3
        },
        {
            "name": "Rodopoli",
            "x": 18755.8,
            "y": 16599.9
        }
    ]
}