{
    "world_size": 12800,
    "map_marker": [
        {
            "name": "outpost",
            "x": 1078.7,
            "y": 11408.5
        },
        {
            "name": "outpost_1",
            "x": 2104.8,
            "y": 11016.4
        },
        {
            "name": "outpost_2",
            "x": 4266.76,
            "y": 10486.6
        },
        {
            "name": "outpost_3",
            "x": 2045.35,
            "y": 7281.85
        },
        {
            "name": "outpost_4",
            "x": 4617.07,
            "y": 6314.85
        },
        {
            "name": "outpost_5",
            "x": 3182.5,
            "y": 4950
        },
        {
            "name": "outpost_6",
            "x": 4544,
            "y": 4745
        },
        {
            "name": "outpost_7",
            "x": 5614.69,
            "y": 3780.36
        },
        {
            "name": "outpost_8",
            "x": 4952.94,
            "y": 2149.14
        },
        {
            "name": "outpost_9",
            "x": 3831.09,
            "y": 1830.39
        },
        {
            "name": "outpost_10",
            "x": 8931.5,
            "y": 2051.5
        },
        {
            "name": "outpost_11",
            "x": 9898.89,
            "y": 3894.99
        },
        {
            "name": "outpost_12",
            "x": 11123.1,
            "y": 2473.31
        },
        {
            "name": "outpost_13",
            "x": 11311.7,
            "y": 4201.98
        },
        {
            "name": "outpost_14",
            "x": 7641.38,
            "y": 5972.13
        },
        {
            "name": "outpost_15",
            "x": 8916.63,
            "y": 6578.5
        },
        {
            "name": "outpost_16",
            "x": 9680.92,
            "y": 8495.7
        },
        {
            "name": "outpost_17",
            "x": 9428.85,
            "y": 10362.9
        },
        {
            "name": "outpost_18",
            "x": 8169.52,
            "y": 10764.7
        },
        {
            "name": "outpost_19",
            "x": 7811.27,
            "y": 10090.7
        },
        {
            "name": "outpost_20",
            "x": 6302.38,
            "y": 9906.25
        },
        {
            "name": "outpost_21",
            "x": 6415.63,
            "y": 8178.38
        },
        {
            "name": "outpost_22",
            "x": 6852.22,
            "y": 11201.4
        },
        {
            "name": "resource",
            "x": 1233.38,
            "y": 8960.63
        },
        {
            "name": "resource_1",
            "x": 2073.13,
            "y": 9473.5
        },
        {
            "name": "resource_2",
            "x": 3126.95,
            "y": 12004.2
        },
        {
            "name": "resource_3",
            "x": 5126.5,
            "y": 10439.5
        },
        {
            "name": "resource_4",
            "x": 3814,
            "y": 8470.38
        },
        {
            "name": "resource_5",
            "x": 1314.24,
            "y": 8015.06
        },
        {
            "name": "resource_6",
            "x": 4852.5,
            "y": 7299.38
        },
        {
            "name": "resource_7",
            "x": 2580.96,
            "y": 5481.05
        },
        {
            "name": "resource_8",
            "x": 5230.88,
            "y": 5671.13
        },
        {
            "name": "resource_9",
            "x": 1664.5,
            "y": 3685
        },
        {
            "name": "resource_10",
            "x": 7648.75,
            "y": 2683.2
        },
        {
            "name": "resource_11",
            "x": 11570,
            "y": 396.982
        },
        {
            "name": "resource_12",
            "x": 7828.88,
            "y": 5847.5
        },
        {
            "name": "resource_13",
            "x": 9073.35,
            "y": 6643.35
        },
        {
            "name": "resource_14",
            "x": 10667.6,
            "y": 6955.64
        },
        {
            "name": "resource_15",
            "x": 9831.25,
            "y": 8087.63
        },
        {
            "name": "factory",
            "x": 11558,
            "y": 7082.75
        },
        {
            "name": "factory_1",
            "x": 9291,
            "y": 11162.6
        },
        {
            "name": "factory_2",
            "x": 1561.47,
            "y": 7548.8
        },
        {
            "name": "factory_3",
            "x": 7328.75,
            "y": 2605.75
        },
        {
            "name": "factory_4",
            "x": 6385.09,
            "y": 4785.98
        },
        {
            "name": "factory_5",
            "x": 3106.37,
            "y": 7071.78
        },
        {
            "name": "factory_6",
            "x": 10999.8,
            "y": 9020.5
        },
        {
            "name": "factory_7",
            "x": 11359.6,
            "y": 9442.61
        },
        {
            "name": "factory_8",
            "x": 11157.2,
            "y": 11439.2
        },
        {
            "name": "airport",
            "x": 3914.02,
            "y": 10210
        },
        {
            "name": "airport_1",
            "x": 6477.38,
            "y": 3804.54
        },
        {
            "name": "airport_2",
            "x": 7887.04,
            "y": 9723.9
        },
        {
            "name": "airport_3",
            "x": 11349.1,
            "y": 8927.58
        },
        {
            "name": "Bielawa",
            "x": 1568.54,
            "y": 9749.7
        },
        {
            "name": "Lukow",
            "x": 3527.17,
            "y": 11972
        },
        {
            "name": "Gliniska",
            "x": 4974.75,
            "y": 9927.96
        },
        {
            "name": "Brena",
            "x": 6607.2,
            "y": 11214.7
        },
        {
            "name": "Tarnow",
            "x": 9298.66,
            "y": 10927
        },
        {
            "name": "Sitnik",
            "x": 11503.2,
            "y": 9636.08
        },
        {
            "name": "Borek",
            "x": 9809.17,
            "y": 8515.95
        },
        {
            "name": "Zapadlisko",
            "x": 8064.63,
            "y": 8719.14
        },
        {
            "name": "Nidek",
            "x": 6099.94,
            "y": 7975.63
        },
        {
            "name": "Topolin",
            "x": 1875.73,
            "y": 7340.5
        },
        {
            "name": "Adam\u00c3\u00b3w",
            "x": 3068.74,
            "y": 6857.95
        },
        {
            "name": "Muratyn",
            "x": 4577.7,
            "y": 6411.38
        },
        {
            "name": "Radunin",
            "x": 7290.76,
            "y": 6499.27
        },
        {
            "name": "Lembork",
            "x": 8700.3,
            "y": 6655
        },
        {
            "name": "Gieralt\u00c3\u00b3w",
            "x": 11251.9,
            "y": 4354.46
        },
        {
            "name": "Nadb\u00c3\u00b3r",
            "x": 6131.42,
            "y": 4069.5
        },
        {
            "name": "Zalesie",
            "x": 899.59,
            "y": 5544.72
        },
        {
            "name": "Huta",
            "x": 5135.11,
            "y": 5502.38
        },
        {
            "name": "Radacz",
            "x": 4018.52,
            "y": 7932.24
        },
        {
            "name": "Olszanka",
            "x": 4820.06,
            "y": 7682.18
        },
        {
            "name": "Lipina",
            "x": 5940.56,
            "y": 6812.46
        },
        {
            "name": "Kolembrody",
            "x": 8409.38,
            "y": 11985.2
        },
        {
            "name": "Karlin",
            "x": 10064.4,
            "y": 6912.99
        },
        {
            "name": "Sob\u00c3\u00b3tka",
            "x": 6297.47,
            "y": 10252.9
        },
        {
            "name": "Roztoka",
            "x": 7706.2,
            "y": 5327.04
        },
        {
            "name": "Polana",
            "x": 3358.89,
            "y": 2156.82
        },
        {
            "name": "Dolnik",
            "x": 11317.8,
            "y": 676.388
        },
        {
            "name": "Grabin",
            "x": 10653.7,
            "y": 11013.3
        }
    ]
}